pyromodz/__init__.py
pyromodz/client.py
pyromodz/dispatcher.py
pyromodz/emoji.py
pyromodz/file_id.py
pyromodz/filters.py
pyromodz/mime_types.py
pyromodz/py.typed
pyromodz/pyroconfig.py
pyromodz/sync.py
pyromodz/utils.py
pyromodz/connection/__init__.py
pyromodz/connection/connection.py
pyromodz/connection/transport/__init__.py
pyromodz/connection/transport/tcp/__init__.py
pyromodz/connection/transport/tcp/tcp.py
pyromodz/connection/transport/tcp/tcp_abridged.py
pyromodz/connection/transport/tcp/tcp_abridged_o.py
pyromodz/connection/transport/tcp/tcp_full.py
pyromodz/connection/transport/tcp/tcp_intermediate.py
pyromodz/connection/transport/tcp/tcp_intermediate_o.py
pyromodz/crypto/__init__.py
pyromodz/crypto/aes.py
pyromodz/crypto/mtproto.py
pyromodz/crypto/prime.py
pyromodz/crypto/rsa.py
pyromodz/enums/__init__.py
pyromodz/enums/auto_name.py
pyromodz/enums/chat_action.py
pyromodz/enums/chat_event_action.py
pyromodz/enums/chat_member_status.py
pyromodz/enums/chat_members_filter.py
pyromodz/enums/chat_type.py
pyromodz/enums/message_entity_type.py
pyromodz/enums/message_media_type.py
pyromodz/enums/message_service_type.py
pyromodz/enums/messages_filter.py
pyromodz/enums/next_code_type.py
pyromodz/enums/parse_mode.py
pyromodz/enums/poll_type.py
pyromodz/enums/sent_code_type.py
pyromodz/enums/user_status.py
pyromodz/errors/__init__.py
pyromodz/errors/rpc_error.py
pyromodz/exceptions/__init__.py
pyromodz/exceptions/listener_stopped.py
pyromodz/exceptions/listener_timeout.py
pyromodz/handlers/__init__.py
pyromodz/handlers/callback_query_handler.py
pyromodz/handlers/chat_join_request_handler.py
pyromodz/handlers/chat_member_updated_handler.py
pyromodz/handlers/chosen_inline_result_handler.py
pyromodz/handlers/deleted_messages_handler.py
pyromodz/handlers/disconnect_handler.py
pyromodz/handlers/edited_message_handler.py
pyromodz/handlers/handler.py
pyromodz/handlers/inline_query_handler.py
pyromodz/handlers/message_handler.py
pyromodz/handlers/poll_handler.py
pyromodz-2.0.2.dist-info/COPYING
pyromodz-2.0.2.dist-info/COPYING.lesser
pyromodz-2.0.2.dist-info/METADATA
pyromodz-2.0.2.dist-info/NOTICE
pyromodz-2.0.2.dist-info/WHEEL
pyromodz-2.0.2.dist-info/top_level.txt
pyromodz-2.0.2.dist-info/RECORD
