Metadata-Version: 2.1
Name: pyromodz
Version: 2.0.2
Summary: Elegant, modern and asynchronous Telegram MTProto API framework in Python for users and bots
Home-page: https://github.com/pyromodz
Download-URL: https://github.com/Kaal-xD/pyromodz/releases/latest
Author: Kaal-xD
Author-email: dan@pyromodz.org
License: LGPLv3
Project-URL: Tracker, https://github.com/Kaal-xD/pyromodz/issues
Project-URL: Community, https://t.me/pyromodz
Project-URL: Source, https://github.com/Kaal-xD/pyromodz
Project-URL: Documentation, https://docs.pyromodz.org
Keywords: telegram chat messenger mtproto api client library python
Classifier: Development Status :: 5 - Production/Stable
Classifier: Intended Audience :: Developers
Classifier: Natural Language :: English
Classifier: License :: OSI Approved :: GNU Lesser General Public License v3 (LGPLv3)
Classifier: Operating System :: OS Independent
Classifier: Programming Language :: Python
Classifier: Programming Language :: Python :: 3
Classifier: Programming Language :: Python :: 3.8
Classifier: Programming Language :: Python :: 3.9
Classifier: Programming Language :: Python :: 3.10
Classifier: Programming Language :: Python :: 3.11
Classifier: Programming Language :: Python :: 3.12
Classifier: Programming Language :: Python :: Implementation
Classifier: Programming Language :: Python :: Implementation :: CPython
Classifier: Programming Language :: Python :: Implementation :: PyPy
Classifier: Topic :: Internet
Classifier: Topic :: Communications
Classifier: Topic :: Communications :: Chat
Classifier: Topic :: Software Development :: Libraries
Classifier: Topic :: Software Development :: Libraries :: Python Modules
Classifier: Topic :: Software Development :: Libraries :: Application Frameworks
Requires-Python: ~=3.8
License-File: COPYING
License-File: COPYING.lesser
License-File: NOTICE
Requires-Dist: pyaes (==1.6.1)
Requires-Dist: pysocks (==1.7.1)
